top/__init__.py
top/app_settings.py
top/apps.py
top/auth_hooks.py
top/models.py
top/task_helpers.py
top/tasks.py
top/urls.py
top/views.py
top/locale/de/LC_MESSAGES/django.mo
top/locale/de/LC_MESSAGES/django.po
top/locale/en/LC_MESSAGES/django.mo
top/locale/en/LC_MESSAGES/django.po
top/migrations/0001_initial.py
top/migrations/__init__.py
top/static/top/aatop.txt
top/templates/top/index-bs5.html
top/templates/top/index.html
aa_top-1.1.0.dist-info/licenses/LICENSE
aa_top-1.1.0.dist-info/WHEEL
aa_top-1.1.0.dist-info/METADATA
aa_top-1.1.0.dist-info/RECORD
