Metadata-Version: 2.4
Name: aa-top
Version: 1.1.0
Summary: Alliance Auth Resource Monitor
Keywords: allianceauth,eveonline
Author-email: Joel Falknau <joel.falknau@gmail.com>
Requires-Python: >=3.10
Classifier: Environment :: Web Environment
Classifier: Framework :: Celery
Classifier: Framework :: Django
Classifier: Framework :: Django :: 4.2
Classifier: Framework :: Django :: 5.2
Classifier: Intended Audience :: Developers
Classifier: License :: OSI Approved :: MIT License
Classifier: Operating System :: OS Independent
Classifier: Programming Language :: Python
Classifier: Programming Language :: Python :: 3 :: Only
Classifier: Programming Language :: Python :: 3.10
Classifier: Programming Language :: Python :: 3.11
Classifier: Programming Language :: Python :: 3.12
Classifier: Programming Language :: Python :: 3.13
Classifier: Programming Language :: Python :: 3.14
Classifier: Programming Language :: Python :: Implementation :: CPython
Classifier: Topic :: Internet :: WWW/HTTP
Classifier: Topic :: Internet :: WWW/HTTP :: Dynamic Content
License-File: LICENSE
Requires-Dist: allianceauth>=4.6.4,<6
Requires-Dist: psutil
Project-URL: Homepage, https://gitlab.com/tactical-supremacy/aa-top
Project-URL: Source, https://gitlab.com/tactical-supremacy/aa-top
Project-URL: Tracker, https://gitlab.com/tactical-supremacy/aa-top/-/issues
